LICENSE.md
MANIFEST.in
README.md
requirements.txt
setup.py
smsfarm/__init__.py
smsfarm/core.py
smsfarm.egg-info/PKG-INFO
smsfarm.egg-info/SOURCES.txt
smsfarm.egg-info/dependency_links.txt
smsfarm.egg-info/not-zip-safe
smsfarm.egg-info/requires.txt
smsfarm.egg-info/top_level.txt
tests/__init__.py
tests/helpers.py
tests/test_client.py