Metadata-Version: 1.1
Name: smsfarm
Version: 1.0.0
Summary: Python client for smsfarm.sk
Home-page: https://github.com/j-mak/smsfarm
Author: Jozef "sunny" Mak
Author-email: sunny@jozefmak.eu
License: MIT License
Keywords: smsfarm,sms-client
Platform: UNKNOWN
Classifier: Development Status :: 3 - Alpha
Classifier: License :: OSI Approved :: MIT License
Classifier: Operating System :: POSIX :: Linux
Classifier: Programming Language :: Python :: 3
Classifier: Programming Language :: Python :: 3 :: Only
Classifier: Topic :: Software Development :: Libraries
Classifier: Topic :: Software Development :: Libraries :: Python Modules
